alignmeet/__init__.py
alignmeet/__main__.py
alignmeet/annotation.py
alignmeet/annotations.py
alignmeet/autoalign.py
alignmeet/clickslider.py
alignmeet/combobox.py
alignmeet/dialog_act.py
alignmeet/evaluation.py
alignmeet/htmldelegate.py
alignmeet/player.py
alignmeet/problems.py
alignmeet/settings.py
alignmeet/icons/arrow-circle-315.png
alignmeet/icons/arrow-return-180-left.png
alignmeet/icons/arrow-return.png
alignmeet/icons/arrow-split-270.png
alignmeet/icons/arrow-stop-090.png
alignmeet/icons/arrow-stop-270.png
alignmeet/icons/layout-join-vertical.png
alignmeet/icons/layout-split-vertical.png
alignmeet/icons/plus.png
alignmeet/minutes/__init__.py
alignmeet/minutes/minutes.py
alignmeet/minutes/minutes_editor.py
alignmeet/minutes/minutes_model.py
alignmeet/transcripts/__init__.py
alignmeet/transcripts/dialog_act_editor.py
alignmeet/transcripts/dialog_act_model.py
alignmeet/transcripts/speaker_editor.py
alignmeet/transcripts/transcript.py
alignmeet/transcripts/transcripts.py
alignmeet-1.0.9.dist-info/METADATA
alignmeet-1.0.9.dist-info/WHEEL
alignmeet-1.0.9.dist-info/entry_points.txt
alignmeet-1.0.9.dist-info/top_level.txt
alignmeet-1.0.9.dist-info/RECORD
