Metadata-Version: 2.1
Name: alignmeet
Version: 1.0.9
Summary: A Comprehensive Tool for Meeting Alignment, Annotation and Evaluation
Home-page: https://github.com/ELITR/alignmeet
Author: Peter Polak
Author-email: polak@ufal.mff.cuni.cz
License: TBD
Requires-Dist: numpy
Requires-Dist: PySide2
Requires-Dist: python-vlc
Requires-Dist: scipy
Requires-Dist: sentence-transformers
